psi_continuum_statespace/__init__.py
psi_continuum_statespace/cli.py
psi_continuum_statespace/consistency.py
psi_continuum_statespace/diagnostics.py
psi_continuum_statespace/plotting.py
psi_continuum_statespace/psi.py
psi_continuum_statespace-0.1.0.dist-info/licenses/LICENSE
psi_continuum_statespace-0.1.0.dist-info/METADATA
psi_continuum_statespace-0.1.0.dist-info/WHEEL
psi_continuum_statespace-0.1.0.dist-info/entry_points.txt
psi_continuum_statespace-0.1.0.dist-info/top_level.txt
psi_continuum_statespace-0.1.0.dist-info/RECORD
