Metadata-Version: 2.4
Name: psi-continuum-statespace
Version: 0.1.0
Summary: Macroscopic state-space diagnostics for late-time cosmic expansion
Author: Dmitry V. Klimov
License-Expression: MIT
Project-URL: Homepage, https://github.com/dmitrylife/psi-continuum-statespace
Project-URL: Documentation, https://psi-continuum.org/docs/v5/
Project-URL: Project, https://psi-continuum.org/theory.html
Project-URL: Source, https://github.com/dmitrylife/psi-continuum-statespace
Project-URL: Issues, https://github.com/dmitrylife/psi-continuum-statespace/issues
Keywords: cosmology,state-space diagnostics,late-time acceleration,dark energy,LCDM,phenomenological cosmology,observational cosmology
Classifier: Development Status :: 5 - Production/Stable
Classifier: Intended Audience :: Science/Research
Classifier: Topic :: Scientific/Engineering :: Astronomy
Classifier: Topic :: Scientific/Engineering :: Physics
Classifier: Operating System :: OS Independent
Classifier: Programming Language :: Python :: 3
Classifier: Programming Language :: Python :: 3.10
Classifier: Programming Language :: Python :: 3.11
Classifier: Programming Language :: Python :: 3.12
Requires-Python: >=3.10
License-File: LICENSE
Requires-Dist: numpy>=1.22
Requires-Dist: matplotlib>=3.6
Requires-Dist: psi-continuum-v2>=0.2.3
Dynamic: license-file
